setup.py
sPyNNaker7.egg-info/PKG-INFO
sPyNNaker7.egg-info/SOURCES.txt
sPyNNaker7.egg-info/dependency_links.txt
sPyNNaker7.egg-info/requires.txt
sPyNNaker7.egg-info/top_level.txt
spynnaker7/__init__.py
spynnaker7/_version.py
spynnaker7/pyNN/__init__.py
spynnaker7/pyNN/_version.py
spynnaker7/pyNN/setup-pynn.py
spynnaker7/pyNN/spinnaker.py
spynnaker7/pyNN/spynnaker7_simulator_interface.py
spynnaker7/pyNN/external_devices/__init__.py
spynnaker7/pyNN/extra_models/__init__.py
spynnaker7/pyNN/models/__init__.py
spynnaker7/pyNN/models/pynn_population.py
spynnaker7/pyNN/models/pynn_projection.py
spynnaker7/pyNN/models/connectors/__init__.py
spynnaker7/pyNN/models/connectors/all_to_all_connector.py
spynnaker7/pyNN/models/connectors/distance_dependent_probability_connector.py
spynnaker7/pyNN/models/connectors/fixed_number_post_connector.py
spynnaker7/pyNN/models/connectors/fixed_number_pre_connector.py
spynnaker7/pyNN/models/connectors/fixed_probability_connector.py
spynnaker7/pyNN/models/connectors/from_file_connector.py
spynnaker7/pyNN/models/connectors/from_list_connector.py
spynnaker7/pyNN/models/connectors/multapse_connector.py
spynnaker7/pyNN/models/connectors/one_to_one_connector.py
spynnaker7/pyNN/models/connectors/small_world_connector.py
spynnaker7/pyNN/models/plasticity_components/__init__.py
spynnaker7/pyNN/models/plasticity_components/timing_dependence/__init__.py
spynnaker7/pyNN/models/plasticity_components/timing_dependence/timing_dependence_spike_pair.py
spynnaker7/pyNN/models/plasticity_components/weight_dependence/__init__.py
spynnaker7/pyNN/models/plasticity_components/weight_dependence/weight_dependence_additive.py
spynnaker7/pyNN/models/plasticity_components/weight_dependence/weight_dependence_additive_triplet.py
spynnaker7/pyNN/models/plasticity_components/weight_dependence/weight_dependence_multiplicative.py
spynnaker7/pyNN/utilities/__init__.py
spynnaker7/pyNN/utilities/spynnaker7_failed_state.py
spynnaker7/pyNN/utilities/random_stats/__init__.py
spynnaker7/pyNN/utilities/random_stats/random_stats_scipy_impl.py
spynnaker7/pyNN/utilities/random_stats/random_stats_uniform_impl.py