Metadata-Version: 1.0
Name: sPyNNaker7
Version: 1!4.0.0
Summary: Extensions of Spinnaker implementation specific for PyNN7
Home-page: https://github.com/SpiNNakerManchester/SpyNNaker7
Author: UNKNOWN
Author-email: UNKNOWN
License: UNKNOWN
Platform: UNKNOWN
